pyaim/__init__.py
pyaim/aimccp.py
pyaim/aimcp.py
pyaim/version.py
pyaim-1.5.4.dist-info/licenses/LICENSE
pyaim-1.5.4.dist-info/METADATA
pyaim-1.5.4.dist-info/WHEEL
pyaim-1.5.4.dist-info/top_level.txt
pyaim-1.5.4.dist-info/RECORD
