Metadata-Version: 2.4
Name: pyaim
Version: 1.5.4
Summary: CyberArk Application Access Manager Client Library for Python 3
Home-page: https://github.com/infamousjoeg/pyaim
Author: Joe Garcia
Author-email: joe.garcia@cyberark.com
License: MIT
Project-URL: Bug Reports, https://github.com/infamousjoeg/pyaim/issues/new?assignees=&labels=&template=bug_report.md&title=
Project-URL: Feature Requests, https://github.com/infamousjoeg/pyaim/issues/new?assignees=&labels=&template=feature_request.md&title=
Project-URL: Source, https://github.com/infamousjoeg/pyaim
Keywords: cyberark,security,vault,aim,aam,privileged access,identity,pam,pim,pas,ccp,cp,credential provider,identity security
Classifier: Programming Language :: Python :: 3 :: Only
Classifier: Development Status :: 5 - Production/Stable
Classifier: Intended Audience :: Developers
Classifier: License :: OSI Approved :: MIT License
Classifier: Operating System :: OS Independent
Classifier: Natural Language :: English
Classifier: Topic :: Office/Business
Classifier: Topic :: Security
Classifier: Topic :: Security :: Cryptography
Classifier: Topic :: Software Development
Classifier: Topic :: Software Development :: Libraries
Classifier: Topic :: Software Development :: Libraries :: Python Modules
Classifier: Topic :: System :: Systems Administration
Classifier: Topic :: Utilities
Requires-Python: >=3.10
License-File: LICENSE
Dynamic: author
Dynamic: author-email
Dynamic: classifier
Dynamic: description
Dynamic: description-content-type
Dynamic: home-page
Dynamic: keywords
Dynamic: license
Dynamic: license-file
Dynamic: project-url
Dynamic: requires-python
Dynamic: summary
